ObservabilityMiddleware/ObservabilityMiddleware.py
ObservabilityMiddleware/__init__.py
ObservabilityMiddleware/other_module.py
tests/__init__.py
tests/test_middleware.py
ObservabilityMiddleware-0.2.3.dist-info/LICENSE
ObservabilityMiddleware-0.2.3.dist-info/METADATA
ObservabilityMiddleware-0.2.3.dist-info/WHEEL
ObservabilityMiddleware-0.2.3.dist-info/top_level.txt
ObservabilityMiddleware-0.2.3.dist-info/RECORD
