Metadata-Version: 2.1
Name: ObservabilityMiddleware
Version: 0.2.3
Summary: A middleware for observability in FastAPI applications
Home-page: https://github.com/rhinuxx/ObservabilityMiddleware
Author: rhinuxx
Author-email: rhinux.x@gmail.com
Classifier: Programming Language :: Python :: 3
Classifier: License :: OSI Approved :: MIT License
Classifier: Operating System :: OS Independent
Requires-Python: >=3.6
License-File: LICENSE
Requires-Dist: prometheus-client
Requires-Dist: python-json-logger
Requires-Dist: ddtrace
